{"apkPath":"/home/reach_24_data//AntennaPod/app/build/outputs/apk/play/debug/app-play-debug.apk","outFolder":["/home/notebooks/reachExpLarge/Antennapod/Antennapod_startForeground"],"componentFilter":[["de.danoeh.antennapod.core.service.playback.*Playback.*","org.connectbot.*GeneratePubkeyActivity.*","org.connectbot.util.*EntropyView.*","org.connectbot.util.*EntropyDialog.*","org.connectbot.util.*PubkeyDatabase.*"]],"specSet":"{\"specs\":[],\"disallow\":[{\"univQuant\":[{\"$type\":\"edu.colorado.plv.bounder.symbolicexecutor.state.NamedPureVar\",\"n\":\"s\"}],\"existQuant\":[],\"pred\":{\"$type\":\"edu.colorado.plv.bounder.lifestate.LifeState.LSTrue\"},\"target\":{\"$type\":\"edu.colorado.plv.bounder.lifestate.LifeState.OAbsMsg\",\"mt\":{\"$type\":\"edu.colorado.plv.bounder.ir.CIEnter\"},\"signatures\":{\"$type\":\"edu.colorado.plv.bounder.lifestate.LifeState.SubClassMatcher\",\"baseSubtypeOf\":[\"android.app.Service\"],\"signatureMatcher\":\"void startForeground\\\\(.*\",\"ident\":\"Service_startForeground\"},\"lsVars\":[{\"$type\":\"edu.colorado.plv.bounder.symbolicexecutor.state.TopVal\"},{\"$type\":\"edu.colorado.plv.bounder.symbolicexecutor.state.NamedPureVar\",\"n\":\"s\"}]}}]}","initialQuery":[{"t":"InitialQueryWithStackTrace","trace":"[{\"$type\":\"edu.colorado.plv.bounder.lifestate.LifeState.ExactClassMatcher\",\"baseMatcher\":\"de\\\\.danoeh\\\\.antennapod\\\\.core\\\\.service\\\\.playback\\\\.PlaybackServiceStateManager\",\"signatureMatcher\":\".* startForeground\\\\(.*\",\"ident\":\"FromTrace_de.danoeh.antennapod.core.service.playback.PlaybackServiceStateManager_startForeground\"},{\"$type\":\"edu.colorado.plv.bounder.lifestate.LifeState.ExactClassMatcher\",\"baseMatcher\":\"de\\\\.danoeh\\\\.antennapod\\\\.core\\\\.service\\\\.playback\\\\.PlaybackService\\\\$3\",\"signatureMatcher\":\".* statusChanged\\\\(.*\",\"ident\":\"FromTrace_de.danoeh.antennapod.core.service.playback.PlaybackService$3_statusChanged\"},{\"$type\":\"edu.colorado.plv.bounder.lifestate.LifeState.ExactClassMatcher\",\"baseMatcher\":\"de\\\\.danoeh\\\\.antennapod\\\\.playback\\\\.base\\\\.PlaybackServiceMediaPlayer\",\"signatureMatcher\":\".* setPlayerStatus\\\\(.*\",\"ident\":\"FromTrace_de.danoeh.antennapod.playback.base.PlaybackServiceMediaPlayer_setPlayerStatus\"},{\"$type\":\"edu.colorado.plv.bounder.lifestate.LifeState.ExactClassMatcher\",\"baseMatcher\":\"de\\\\.danoeh\\\\.antennapod\\\\.playback\\\\.base\\\\.PlaybackServiceMediaPlayer\",\"signatureMatcher\":\".* setPlayerStatus\\\\(.*\",\"ident\":\"FromTrace_de.danoeh.antennapod.playback.base.PlaybackServiceMediaPlayer_setPlayerStatus\"},{\"$type\":\"edu.colorado.plv.bounder.lifestate.LifeState.ExactClassMatcher\",\"baseMatcher\":\"de\\\\.danoeh\\\\.antennapod\\\\.core\\\\.service\\\\.playback\\\\.LocalPSMP\",\"signatureMatcher\":\".* resume\\\\(.*\",\"ident\":\"FromTrace_de.danoeh.antennapod.core.service.playback.LocalPSMP_resume\"},{\"$type\":\"edu.colorado.plv.bounder.lifestate.LifeState.ExactClassMatcher\",\"baseMatcher\":\"de\\\\.danoeh\\\\.antennapod\\\\.core\\\\.service\\\\.playback\\\\.PlaybackService\",\"signatureMatcher\":\".* resume\\\\(.*\",\"ident\":\"FromTrace_de.danoeh.antennapod.core.service.playback.PlaybackService_resume\"},{\"$type\":\"edu.colorado.plv.bounder.lifestate.LifeState.ExactClassMatcher\",\"baseMatcher\":\"de\\\\.danoeh\\\\.antennapod\\\\.core\\\\.service\\\\.playback\\\\.PlaybackService\\\\$9\",\"signatureMatcher\":\".* onPlay\\\\(.*\",\"ident\":\"FromTrace_de.danoeh.antennapod.core.service.playback.PlaybackService$9_onPlay\"}]","internalQry":"{\"t\":\"DisallowedCallin\",\"className\":\"de.danoeh.antennapod.core.service.playback.PlaybackServiceStateManager\",\"methodName\":\"void startForeground(int,android.app.Notification)\",\"s\":\"{\\\"univQuant\\\":[{\\\"$type\\\":\\\"edu.colorado.plv.bounder.symbolicexecutor.state.NamedPureVar\\\",\\\"n\\\":\\\"s\\\"}],\\\"existQuant\\\":[],\\\"pred\\\":{\\\"$type\\\":\\\"edu.colorado.plv.bounder.lifestate.LifeState.LSTrue\\\"},\\\"target\\\":{\\\"$type\\\":\\\"edu.colorado.plv.bounder.lifestate.LifeState.OAbsMsg\\\",\\\"mt\\\":{\\\"$type\\\":\\\"edu.colorado.plv.bounder.ir.CIEnter\\\"},\\\"signatures\\\":{\\\"$type\\\":\\\"edu.colorado.plv.bounder.lifestate.LifeState.SubClassMatcher\\\",\\\"baseSubtypeOf\\\":[\\\"android.app.Service\\\"],\\\"signatureMatcher\\\":\\\"void startForeground\\\\\\\\(.*\\\",\\\"ident\\\":\\\"Service_startForeground\\\"},\\\"lsVars\\\":[{\\\"$type\\\":\\\"edu.colorado.plv.bounder.symbolicexecutor.state.TopVal\\\"},{\\\"$type\\\":\\\"edu.colorado.plv.bounder.symbolicexecutor.state.NamedPureVar\\\",\\\"n\\\":\\\"s\\\"}]}}\"}"}],"timeLimit":2147483647,"truncateOut":false,"approxMode":{"$type":"edu.colorado.plv.bounder.symbolicexecutor.PreciseApproxMode","canWeaken":true,"dropStatePolicy":[{"$type":"edu.colorado.plv.bounder.symbolicexecutor.LimitLocationVisitDropStatePolicy","limit":3},{"$type":"edu.colorado.plv.bounder.symbolicexecutor.LimitAppRecursionDropStatePolicy","calls":3},{"$type":"edu.colorado.plv.bounder.symbolicexecutor.LimitMaterializedFieldsDropStatePolicy","nameCount":{"*":2}},{"$type":"edu.colorado.plv.bounder.symbolicexecutor.DumpTraceAtLocationPolicy","appMethod":[{"$type":"edu.colorado.plv.bounder.lifestate.LifeState.ExactClassMatcher","baseMatcher":"de\\.danoeh\\.antennapod\\.core\\.service\\.playback\\.PlaybackServiceStateManager","signatureMatcher":".* startForeground\\(.*","ident":"FromTrace_de.danoeh.antennapod.core.service.playback.PlaybackServiceStateManager_startForeground"}],"findLine":[],"outputFolder":"/home/notebooks/reachExpLarge/Antennapod/Antennapod_startForeground","dumpAtCallbacks":true},{"$type":"edu.colorado.plv.bounder.symbolicexecutor.DumpTraceAtLocationPolicy","appMethod":[{"$type":"edu.colorado.plv.bounder.lifestate.LifeState.ExactClassMatcher","baseMatcher":"de\\.danoeh\\.antennapod\\.core\\.service\\.playback\\.PlaybackService\\$3","signatureMatcher":".* statusChanged\\(.*","ident":"FromTrace_de.danoeh.antennapod.core.service.playback.PlaybackService$3_statusChanged"}],"findLine":[],"outputFolder":"/home/notebooks/reachExpLarge/Antennapod/Antennapod_startForeground","dumpAtCallbacks":true},{"$type":"edu.colorado.plv.bounder.symbolicexecutor.DumpTraceAtLocationPolicy","appMethod":[{"$type":"edu.colorado.plv.bounder.lifestate.LifeState.ExactClassMatcher","baseMatcher":"de\\.danoeh\\.antennapod\\.playback\\.base\\.PlaybackServiceMediaPlayer","signatureMatcher":".* setPlayerStatus\\(.*","ident":"FromTrace_de.danoeh.antennapod.playback.base.PlaybackServiceMediaPlayer_setPlayerStatus"}],"findLine":[],"outputFolder":"/home/notebooks/reachExpLarge/Antennapod/Antennapod_startForeground","dumpAtCallbacks":true},{"$type":"edu.colorado.plv.bounder.symbolicexecutor.DumpTraceAtLocationPolicy","appMethod":[{"$type":"edu.colorado.plv.bounder.lifestate.LifeState.ExactClassMatcher","baseMatcher":"de\\.danoeh\\.antennapod\\.playback\\.base\\.PlaybackServiceMediaPlayer","signatureMatcher":".* setPlayerStatus\\(.*","ident":"FromTrace_de.danoeh.antennapod.playback.base.PlaybackServiceMediaPlayer_setPlayerStatus"}],"findLine":[],"outputFolder":"/home/notebooks/reachExpLarge/Antennapod/Antennapod_startForeground","dumpAtCallbacks":true},{"$type":"edu.colorado.plv.bounder.symbolicexecutor.DumpTraceAtLocationPolicy","appMethod":[{"$type":"edu.colorado.plv.bounder.lifestate.LifeState.ExactClassMatcher","baseMatcher":"de\\.danoeh\\.antennapod\\.core\\.service\\.playback\\.LocalPSMP","signatureMatcher":".* resume\\(.*","ident":"FromTrace_de.danoeh.antennapod.core.service.playback.LocalPSMP_resume"}],"findLine":[],"outputFolder":"/home/notebooks/reachExpLarge/Antennapod/Antennapod_startForeground","dumpAtCallbacks":true},{"$type":"edu.colorado.plv.bounder.symbolicexecutor.DumpTraceAtLocationPolicy","appMethod":[{"$type":"edu.colorado.plv.bounder.lifestate.LifeState.ExactClassMatcher","baseMatcher":"de\\.danoeh\\.antennapod\\.core\\.service\\.playback\\.PlaybackService","signatureMatcher":".* resume\\(.*","ident":"FromTrace_de.danoeh.antennapod.core.service.playback.PlaybackService_resume"}],"findLine":[],"outputFolder":"/home/notebooks/reachExpLarge/Antennapod/Antennapod_startForeground","dumpAtCallbacks":true},{"$type":"edu.colorado.plv.bounder.symbolicexecutor.DumpTraceAtLocationPolicy","appMethod":[{"$type":"edu.colorado.plv.bounder.lifestate.LifeState.ExactClassMatcher","baseMatcher":"de\\.danoeh\\.antennapod\\.core\\.service\\.playback\\.PlaybackService\\$9","signatureMatcher":".* onPlay\\(.*","ident":"FromTrace_de.danoeh.antennapod.core.service.playback.PlaybackService$9_onPlay"}],"findLine":[],"outputFolder":"/home/notebooks/reachExpLarge/Antennapod/Antennapod_startForeground","dumpAtCallbacks":true}]},"z3TimeoutBehavior":[{"subsumeTryTimeLimit":[200000]}]}